optprc/Asian.py
optprc/IRS.py
optprc/Vanilla.py
optprc/__init__.py
optprc/cdspricing.py
optprc/iData.py
optprc/iDate.py
optprc/iMath.py
optprc/dll/__init__.py
optprc/dll/jpmcds.pyd
optprc/dll/jpmcds.so
optprc/dll/libboost_python37-mgw81-mt-x64-1_69.dll
optprc/dll/libboost_python37.so
optprc/dll/libboost_python37.so.1.69.0
optprc-0.2.0.dist-info/LICENSE
optprc-0.2.0.dist-info/METADATA
optprc-0.2.0.dist-info/WHEEL
optprc-0.2.0.dist-info/top_level.txt
optprc-0.2.0.dist-info/RECORD
