Metadata-Version: 2.1
Name: optprc
Version: 0.2.0
Summary: option pricer
Home-page: https://www.optprc.com
Author: Julian Gong
Author-email: juliangong@hotmail.com
License: UNKNOWN
Platform: UNKNOWN
Classifier: Programming Language :: Python :: 3.7
Classifier: License :: OSI Approved :: MIT License
Classifier: Operating System :: OS Independent
